// class version 50.0 (50)
// access flags 0x401
public abstract class TAlloyInteraction$$6$class {


  // access flags 0x9
  public static $init$(LTAlloyInteraction$$6;)V
    RETURN
    MAXSTACK = 1
    MAXLOCALS = 1

  // access flags 0x9
  public static bindPart(LTAlloyInteraction$$6;Lcodechicken/multipart/TMultiPart;)V
    ALOAD 0
    ALOAD 1
    INVOKEINTERFACE TAlloyInteraction$$6.TAlloyInteraction$$6$$super$bindPart (Lcodechicken/multipart/TMultiPart;)V
    ALOAD 1
    INSTANCEOF mekanism/api/IAlloyInteraction
    IFEQ L0
    ALOAD 0
    ALOAD 1
    CHECKCAST mekanism/api/IAlloyInteraction
    INVOKEINTERFACE TAlloyInteraction$$6.TAlloyInteraction$$6$$impl_$eq (Lmekanism/api/IAlloyInteraction;)V
   L0
   FRAME FULL [TAlloyInteraction$$6 codechicken/multipart/TMultiPart] []
    RETURN
    MAXSTACK = 2
    MAXLOCALS = 2

  // access flags 0x9
  public static partRemoved(LTAlloyInteraction$$6;Lcodechicken/multipart/TMultiPart;I)V
    ALOAD 0
    ALOAD 1
    ILOAD 2
    INVOKEINTERFACE TAlloyInteraction$$6.TAlloyInteraction$$6$$super$partRemoved (Lcodechicken/multipart/TMultiPart;I)V
    ALOAD 1
    ALOAD 0
    INVOKEINTERFACE TAlloyInteraction$$6.TAlloyInteraction$$6$$impl ()Lmekanism/api/IAlloyInteraction;
    IF_ACMPNE L0
    ALOAD 0
    ACONST_NULL
    INVOKEINTERFACE TAlloyInteraction$$6.TAlloyInteraction$$6$$impl_$eq (Lmekanism/api/IAlloyInteraction;)V
   L0
   FRAME FULL [TAlloyInteraction$$6 codechicken/multipart/TMultiPart I] []
    RETURN
    MAXSTACK = 3
    MAXLOCALS = 3

  // access flags 0x9
  public static canAddPart(LTAlloyInteraction$$6;Lcodechicken/multipart/TMultiPart;)Z
    ALOAD 0
    INVOKEINTERFACE TAlloyInteraction$$6.TAlloyInteraction$$6$$impl ()Lmekanism/api/IAlloyInteraction;
    IFNULL L0
    ALOAD 1
    INSTANCEOF mekanism/api/IAlloyInteraction
    IFEQ L0
    ICONST_0
    IRETURN
   L0
   FRAME FULL [TAlloyInteraction$$6 codechicken/multipart/TMultiPart] []
    ALOAD 0
    ALOAD 1
    INVOKEINTERFACE TAlloyInteraction$$6.TAlloyInteraction$$6$$super$canAddPart (Lcodechicken/multipart/TMultiPart;)Z
    IRETURN
    MAXSTACK = 2
    MAXLOCALS = 2

  // access flags 0x9
  public static onAlloyInteraction(LTAlloyInteraction$$6;Lnet/minecraft/entity/player/EntityPlayer;I)V
    ALOAD 0
    INVOKEINTERFACE TAlloyInteraction$$6.TAlloyInteraction$$6$$impl ()Lmekanism/api/IAlloyInteraction;
    ALOAD 1
    ILOAD 2
    INVOKEINTERFACE mekanism/api/IAlloyInteraction.onAlloyInteraction (Lnet/minecraft/entity/player/EntityPlayer;I)V
    RETURN
    MAXSTACK = 3
    MAXLOCALS = 3

  // access flags 0x9
  public static copyFrom(LTAlloyInteraction$$6;Lcodechicken/multipart/TileMultipart;)V
    ALOAD 0
    ALOAD 1
    INVOKEINTERFACE TAlloyInteraction$$6.TAlloyInteraction$$6$$super$copyFrom (Lcodechicken/multipart/TileMultipart;)V
    ALOAD 1
    INSTANCEOF TAlloyInteraction$$6
    IFEQ L0
    ALOAD 0
    ALOAD 1
    INVOKEINTERFACE TAlloyInteraction$$6.TAlloyInteraction$$6$$impl ()Lmekanism/api/IAlloyInteraction;
    INVOKEINTERFACE TAlloyInteraction$$6.TAlloyInteraction$$6$$impl_$eq (Lmekanism/api/IAlloyInteraction;)V
   L0
    RETURN
    MAXSTACK = 2
    MAXLOCALS = 2
}
