// class version 50.0 (50)
// access flags 0x401
public abstract class TBlockableConnection$$4$class {


  // access flags 0x9
  public static $init$(LTBlockableConnection$$4;)V
    RETURN
    MAXSTACK = 1
    MAXLOCALS = 1

  // access flags 0x9
  public static bindPart(LTBlockableConnection$$4;Lcodechicken/multipart/TMultiPart;)V
    ALOAD 0
    ALOAD 1
    INVOKEINTERFACE TBlockableConnection$$4.TBlockableConnection$$4$$super$bindPart (Lcodechicken/multipart/TMultiPart;)V
    ALOAD 1
    INSTANCEOF mekanism/api/transmitters/IBlockableConnection
    IFEQ L0
    ALOAD 0
    ALOAD 1
    CHECKCAST mekanism/api/transmitters/IBlockableConnection
    INVOKEINTERFACE TBlockableConnection$$4.TBlockableConnection$$4$$impl_$eq (Lmekanism/api/transmitters/IBlockableConnection;)V
   L0
   FRAME FULL [TBlockableConnection$$4 codechicken/multipart/TMultiPart] []
    RETURN
    MAXSTACK = 2
    MAXLOCALS = 2

  // access flags 0x9
  public static partRemoved(LTBlockableConnection$$4;Lcodechicken/multipart/TMultiPart;I)V
    ALOAD 0
    ALOAD 1
    ILOAD 2
    INVOKEINTERFACE TBlockableConnection$$4.TBlockableConnection$$4$$super$partRemoved (Lcodechicken/multipart/TMultiPart;I)V
    ALOAD 1
    ALOAD 0
    INVOKEINTERFACE TBlockableConnection$$4.TBlockableConnection$$4$$impl ()Lmekanism/api/transmitters/IBlockableConnection;
    IF_ACMPNE L0
    ALOAD 0
    ACONST_NULL
    INVOKEINTERFACE TBlockableConnection$$4.TBlockableConnection$$4$$impl_$eq (Lmekanism/api/transmitters/IBlockableConnection;)V
   L0
   FRAME FULL [TBlockableConnection$$4 codechicken/multipart/TMultiPart I] []
    RETURN
    MAXSTACK = 3
    MAXLOCALS = 3

  // access flags 0x9
  public static canAddPart(LTBlockableConnection$$4;Lcodechicken/multipart/TMultiPart;)Z
    ALOAD 0
    INVOKEINTERFACE TBlockableConnection$$4.TBlockableConnection$$4$$impl ()Lmekanism/api/transmitters/IBlockableConnection;
    IFNULL L0
    ALOAD 1
    INSTANCEOF mekanism/api/transmitters/IBlockableConnection
    IFEQ L0
    ICONST_0
    IRETURN
   L0
   FRAME FULL [TBlockableConnection$$4 codechicken/multipart/TMultiPart] []
    ALOAD 0
    ALOAD 1
    INVOKEINTERFACE TBlockableConnection$$4.TBlockableConnection$$4$$super$canAddPart (Lcodechicken/multipart/TMultiPart;)Z
    IRETURN
    MAXSTACK = 2
    MAXLOCALS = 2

  // access flags 0x9
  public static canConnectMutual(LTBlockableConnection$$4;Lnet/minecraftforge/common/util/ForgeDirection;)Z
    ALOAD 0
    INVOKEINTERFACE TBlockableConnection$$4.TBlockableConnection$$4$$impl ()Lmekanism/api/transmitters/IBlockableConnection;
    ALOAD 1
    INVOKEINTERFACE mekanism/api/transmitters/IBlockableConnection.canConnectMutual (Lnet/minecraftforge/common/util/ForgeDirection;)Z
    IRETURN
    MAXSTACK = 2
    MAXLOCALS = 2

  // access flags 0x9
  public static canConnect(LTBlockableConnection$$4;Lnet/minecraftforge/common/util/ForgeDirection;)Z
    ALOAD 0
    INVOKEINTERFACE TBlockableConnection$$4.TBlockableConnection$$4$$impl ()Lmekanism/api/transmitters/IBlockableConnection;
    ALOAD 1
    INVOKEINTERFACE mekanism/api/transmitters/IBlockableConnection.canConnect (Lnet/minecraftforge/common/util/ForgeDirection;)Z
    IRETURN
    MAXSTACK = 2
    MAXLOCALS = 2

  // access flags 0x9
  public static copyFrom(LTBlockableConnection$$4;Lcodechicken/multipart/TileMultipart;)V
    ALOAD 0
    ALOAD 1
    INVOKEINTERFACE TBlockableConnection$$4.TBlockableConnection$$4$$super$copyFrom (Lcodechicken/multipart/TileMultipart;)V
    ALOAD 1
    INSTANCEOF TBlockableConnection$$4
    IFEQ L0
    ALOAD 0
    ALOAD 1
    INVOKEINTERFACE TBlockableConnection$$4.TBlockableConnection$$4$$impl ()Lmekanism/api/transmitters/IBlockableConnection;
    INVOKEINTERFACE TBlockableConnection$$4.TBlockableConnection$$4$$impl_$eq (Lmekanism/api/transmitters/IBlockableConnection;)V
   L0
    RETURN
    MAXSTACK = 2
    MAXLOCALS = 2
}
