// class version 50.0 (50)
// access flags 0x401
public abstract class TConfigurable$$0$class {


  // access flags 0x9
  public static $init$(LTConfigurable$$0;)V
    RETURN
    MAXSTACK = 1
    MAXLOCALS = 1

  // access flags 0x9
  public static bindPart(LTConfigurable$$0;Lcodechicken/multipart/TMultiPart;)V
    ALOAD 0
    ALOAD 1
    INVOKEINTERFACE TConfigurable$$0.TConfigurable$$0$$super$bindPart (Lcodechicken/multipart/TMultiPart;)V
    ALOAD 1
    INSTANCEOF mekanism/api/IConfigurable
    IFEQ L0
    ALOAD 0
    ALOAD 1
    CHECKCAST mekanism/api/IConfigurable
    INVOKEINTERFACE TConfigurable$$0.TConfigurable$$0$$impl_$eq (Lmekanism/api/IConfigurable;)V
   L0
   FRAME FULL [TConfigurable$$0 codechicken/multipart/TMultiPart] []
    RETURN
    MAXSTACK = 2
    MAXLOCALS = 2

  // access flags 0x9
  public static partRemoved(LTConfigurable$$0;Lcodechicken/multipart/TMultiPart;I)V
    ALOAD 0
    ALOAD 1
    ILOAD 2
    INVOKEINTERFACE TConfigurable$$0.TConfigurable$$0$$super$partRemoved (Lcodechicken/multipart/TMultiPart;I)V
    ALOAD 1
    ALOAD 0
    INVOKEINTERFACE TConfigurable$$0.TConfigurable$$0$$impl ()Lmekanism/api/IConfigurable;
    IF_ACMPNE L0
    ALOAD 0
    ACONST_NULL
    INVOKEINTERFACE TConfigurable$$0.TConfigurable$$0$$impl_$eq (Lmekanism/api/IConfigurable;)V
   L0
   FRAME FULL [TConfigurable$$0 codechicken/multipart/TMultiPart I] []
    RETURN
    MAXSTACK = 3
    MAXLOCALS = 3

  // access flags 0x9
  public static canAddPart(LTConfigurable$$0;Lcodechicken/multipart/TMultiPart;)Z
    ALOAD 0
    INVOKEINTERFACE TConfigurable$$0.TConfigurable$$0$$impl ()Lmekanism/api/IConfigurable;
    IFNULL L0
    ALOAD 1
    INSTANCEOF mekanism/api/IConfigurable
    IFEQ L0
    ICONST_0
    IRETURN
   L0
   FRAME FULL [TConfigurable$$0 codechicken/multipart/TMultiPart] []
    ALOAD 0
    ALOAD 1
    INVOKEINTERFACE TConfigurable$$0.TConfigurable$$0$$super$canAddPart (Lcodechicken/multipart/TMultiPart;)Z
    IRETURN
    MAXSTACK = 2
    MAXLOCALS = 2

  // access flags 0x9
  public static onSneakRightClick(LTConfigurable$$0;Lnet/minecraft/entity/player/EntityPlayer;I)Z
    ALOAD 0
    INVOKEINTERFACE TConfigurable$$0.TConfigurable$$0$$impl ()Lmekanism/api/IConfigurable;
    ALOAD 1
    ILOAD 2
    INVOKEINTERFACE mekanism/api/IConfigurable.onSneakRightClick (Lnet/minecraft/entity/player/EntityPlayer;I)Z
    IRETURN
    MAXSTACK = 3
    MAXLOCALS = 3

  // access flags 0x9
  public static onRightClick(LTConfigurable$$0;Lnet/minecraft/entity/player/EntityPlayer;I)Z
    ALOAD 0
    INVOKEINTERFACE TConfigurable$$0.TConfigurable$$0$$impl ()Lmekanism/api/IConfigurable;
    ALOAD 1
    ILOAD 2
    INVOKEINTERFACE mekanism/api/IConfigurable.onRightClick (Lnet/minecraft/entity/player/EntityPlayer;I)Z
    IRETURN
    MAXSTACK = 3
    MAXLOCALS = 3

  // access flags 0x9
  public static copyFrom(LTConfigurable$$0;Lcodechicken/multipart/TileMultipart;)V
    ALOAD 0
    ALOAD 1
    INVOKEINTERFACE TConfigurable$$0.TConfigurable$$0$$super$copyFrom (Lcodechicken/multipart/TileMultipart;)V
    ALOAD 1
    INSTANCEOF TConfigurable$$0
    IFEQ L0
    ALOAD 0
    ALOAD 1
    INVOKEINTERFACE TConfigurable$$0.TConfigurable$$0$$impl ()Lmekanism/api/IConfigurable;
    INVOKEINTERFACE TConfigurable$$0.TConfigurable$$0$$impl_$eq (Lmekanism/api/IConfigurable;)V
   L0
    RETURN
    MAXSTACK = 2
    MAXLOCALS = 2
}
