// class version 50.0 (50)
// access flags 0x401
public abstract class THeatTransfer$$3$class {


  // access flags 0x9
  public static $init$(LTHeatTransfer$$3;)V
    RETURN
    MAXSTACK = 1
    MAXLOCALS = 1

  // access flags 0x9
  public static bindPart(LTHeatTransfer$$3;Lcodechicken/multipart/TMultiPart;)V
    ALOAD 0
    ALOAD 1
    INVOKEINTERFACE THeatTransfer$$3.THeatTransfer$$3$$super$bindPart (Lcodechicken/multipart/TMultiPart;)V
    ALOAD 1
    INSTANCEOF mekanism/api/IHeatTransfer
    IFEQ L0
    ALOAD 0
    ALOAD 1
    CHECKCAST mekanism/api/IHeatTransfer
    INVOKEINTERFACE THeatTransfer$$3.THeatTransfer$$3$$impl_$eq (Lmekanism/api/IHeatTransfer;)V
   L0
   FRAME FULL [THeatTransfer$$3 codechicken/multipart/TMultiPart] []
    RETURN
    MAXSTACK = 2
    MAXLOCALS = 2

  // access flags 0x9
  public static partRemoved(LTHeatTransfer$$3;Lcodechicken/multipart/TMultiPart;I)V
    ALOAD 0
    ALOAD 1
    ILOAD 2
    INVOKEINTERFACE THeatTransfer$$3.THeatTransfer$$3$$super$partRemoved (Lcodechicken/multipart/TMultiPart;I)V
    ALOAD 1
    ALOAD 0
    INVOKEINTERFACE THeatTransfer$$3.THeatTransfer$$3$$impl ()Lmekanism/api/IHeatTransfer;
    IF_ACMPNE L0
    ALOAD 0
    ACONST_NULL
    INVOKEINTERFACE THeatTransfer$$3.THeatTransfer$$3$$impl_$eq (Lmekanism/api/IHeatTransfer;)V
   L0
   FRAME FULL [THeatTransfer$$3 codechicken/multipart/TMultiPart I] []
    RETURN
    MAXSTACK = 3
    MAXLOCALS = 3

  // access flags 0x9
  public static canAddPart(LTHeatTransfer$$3;Lcodechicken/multipart/TMultiPart;)Z
    ALOAD 0
    INVOKEINTERFACE THeatTransfer$$3.THeatTransfer$$3$$impl ()Lmekanism/api/IHeatTransfer;
    IFNULL L0
    ALOAD 1
    INSTANCEOF mekanism/api/IHeatTransfer
    IFEQ L0
    ICONST_0
    IRETURN
   L0
   FRAME FULL [THeatTransfer$$3 codechicken/multipart/TMultiPart] []
    ALOAD 0
    ALOAD 1
    INVOKEINTERFACE THeatTransfer$$3.THeatTransfer$$3$$super$canAddPart (Lcodechicken/multipart/TMultiPart;)Z
    IRETURN
    MAXSTACK = 2
    MAXLOCALS = 2

  // access flags 0x9
  public static getInsulationCoefficient(LTHeatTransfer$$3;Lnet/minecraftforge/common/util/ForgeDirection;)D
    ALOAD 0
    INVOKEINTERFACE THeatTransfer$$3.THeatTransfer$$3$$impl ()Lmekanism/api/IHeatTransfer;
    ALOAD 1
    INVOKEINTERFACE mekanism/api/IHeatTransfer.getInsulationCoefficient (Lnet/minecraftforge/common/util/ForgeDirection;)D
    DRETURN
    MAXSTACK = 2
    MAXLOCALS = 2

  // access flags 0x9
  public static applyTemperatureChange(LTHeatTransfer$$3;)D
    ALOAD 0
    INVOKEINTERFACE THeatTransfer$$3.THeatTransfer$$3$$impl ()Lmekanism/api/IHeatTransfer;
    INVOKEINTERFACE mekanism/api/IHeatTransfer.applyTemperatureChange ()D
    DRETURN
    MAXSTACK = 2
    MAXLOCALS = 1

  // access flags 0x9
  public static getAdjacent(LTHeatTransfer$$3;Lnet/minecraftforge/common/util/ForgeDirection;)Lmekanism/api/IHeatTransfer;
    ALOAD 0
    INVOKEINTERFACE THeatTransfer$$3.THeatTransfer$$3$$impl ()Lmekanism/api/IHeatTransfer;
    ALOAD 1
    INVOKEINTERFACE mekanism/api/IHeatTransfer.getAdjacent (Lnet/minecraftforge/common/util/ForgeDirection;)Lmekanism/api/IHeatTransfer;
    ARETURN
    MAXSTACK = 2
    MAXLOCALS = 2

  // access flags 0x9
  public static canConnectHeat(LTHeatTransfer$$3;Lnet/minecraftforge/common/util/ForgeDirection;)Z
    ALOAD 0
    INVOKEINTERFACE THeatTransfer$$3.THeatTransfer$$3$$impl ()Lmekanism/api/IHeatTransfer;
    ALOAD 1
    INVOKEINTERFACE mekanism/api/IHeatTransfer.canConnectHeat (Lnet/minecraftforge/common/util/ForgeDirection;)Z
    IRETURN
    MAXSTACK = 2
    MAXLOCALS = 2

  // access flags 0x9
  public static transferHeatTo(LTHeatTransfer$$3;D)V
    ALOAD 0
    INVOKEINTERFACE THeatTransfer$$3.THeatTransfer$$3$$impl ()Lmekanism/api/IHeatTransfer;
    DLOAD 1
    INVOKEINTERFACE mekanism/api/IHeatTransfer.transferHeatTo (D)V
    RETURN
    MAXSTACK = 3
    MAXLOCALS = 3

  // access flags 0x9
  public static getTemp(LTHeatTransfer$$3;)D
    ALOAD 0
    INVOKEINTERFACE THeatTransfer$$3.THeatTransfer$$3$$impl ()Lmekanism/api/IHeatTransfer;
    INVOKEINTERFACE mekanism/api/IHeatTransfer.getTemp ()D
    DRETURN
    MAXSTACK = 2
    MAXLOCALS = 1

  // access flags 0x9
  public static getInverseConductionCoefficient(LTHeatTransfer$$3;)D
    ALOAD 0
    INVOKEINTERFACE THeatTransfer$$3.THeatTransfer$$3$$impl ()Lmekanism/api/IHeatTransfer;
    INVOKEINTERFACE mekanism/api/IHeatTransfer.getInverseConductionCoefficient ()D
    DRETURN
    MAXSTACK = 2
    MAXLOCALS = 1

  // access flags 0x9
  public static simulateHeat(LTHeatTransfer$$3;)[D
    ALOAD 0
    INVOKEINTERFACE THeatTransfer$$3.THeatTransfer$$3$$impl ()Lmekanism/api/IHeatTransfer;
    INVOKEINTERFACE mekanism/api/IHeatTransfer.simulateHeat ()[D
    ARETURN
    MAXSTACK = 1
    MAXLOCALS = 1

  // access flags 0x9
  public static copyFrom(LTHeatTransfer$$3;Lcodechicken/multipart/TileMultipart;)V
    ALOAD 0
    ALOAD 1
    INVOKEINTERFACE THeatTransfer$$3.THeatTransfer$$3$$super$copyFrom (Lcodechicken/multipart/TileMultipart;)V
    ALOAD 1
    INSTANCEOF THeatTransfer$$3
    IFEQ L0
    ALOAD 0
    ALOAD 1
    INVOKEINTERFACE THeatTransfer$$3.THeatTransfer$$3$$impl ()Lmekanism/api/IHeatTransfer;
    INVOKEINTERFACE THeatTransfer$$3.THeatTransfer$$3$$impl_$eq (Lmekanism/api/IHeatTransfer;)V
   L0
    RETURN
    MAXSTACK = 2
    MAXLOCALS = 2
}
