// class version 50.0 (50)
// access flags 0x401
public abstract class TStrictEnergyAcceptor$$1$class {


  // access flags 0x9
  public static $init$(LTStrictEnergyAcceptor$$1;)V
    RETURN
    MAXSTACK = 1
    MAXLOCALS = 1

  // access flags 0x9
  public static bindPart(LTStrictEnergyAcceptor$$1;Lcodechicken/multipart/TMultiPart;)V
    ALOAD 0
    ALOAD 1
    INVOKEINTERFACE TStrictEnergyAcceptor$$1.TStrictEnergyAcceptor$$1$$super$bindPart (Lcodechicken/multipart/TMultiPart;)V
    ALOAD 1
    INSTANCEOF mekanism/api/energy/IStrictEnergyAcceptor
    IFEQ L0
    ALOAD 0
    ALOAD 1
    CHECKCAST mekanism/api/energy/IStrictEnergyAcceptor
    INVOKEINTERFACE TStrictEnergyAcceptor$$1.TStrictEnergyAcceptor$$1$$impl_$eq (Lmekanism/api/energy/IStrictEnergyAcceptor;)V
   L0
   FRAME FULL [TStrictEnergyAcceptor$$1 codechicken/multipart/TMultiPart] []
    RETURN
    MAXSTACK = 2
    MAXLOCALS = 2

  // access flags 0x9
  public static partRemoved(LTStrictEnergyAcceptor$$1;Lcodechicken/multipart/TMultiPart;I)V
    ALOAD 0
    ALOAD 1
    ILOAD 2
    INVOKEINTERFACE TStrictEnergyAcceptor$$1.TStrictEnergyAcceptor$$1$$super$partRemoved (Lcodechicken/multipart/TMultiPart;I)V
    ALOAD 1
    ALOAD 0
    INVOKEINTERFACE TStrictEnergyAcceptor$$1.TStrictEnergyAcceptor$$1$$impl ()Lmekanism/api/energy/IStrictEnergyAcceptor;
    IF_ACMPNE L0
    ALOAD 0
    ACONST_NULL
    INVOKEINTERFACE TStrictEnergyAcceptor$$1.TStrictEnergyAcceptor$$1$$impl_$eq (Lmekanism/api/energy/IStrictEnergyAcceptor;)V
   L0
   FRAME FULL [TStrictEnergyAcceptor$$1 codechicken/multipart/TMultiPart I] []
    RETURN
    MAXSTACK = 3
    MAXLOCALS = 3

  // access flags 0x9
  public static canAddPart(LTStrictEnergyAcceptor$$1;Lcodechicken/multipart/TMultiPart;)Z
    ALOAD 0
    INVOKEINTERFACE TStrictEnergyAcceptor$$1.TStrictEnergyAcceptor$$1$$impl ()Lmekanism/api/energy/IStrictEnergyAcceptor;
    IFNULL L0
    ALOAD 1
    INSTANCEOF mekanism/api/energy/IStrictEnergyAcceptor
    IFEQ L0
    ICONST_0
    IRETURN
   L0
   FRAME FULL [TStrictEnergyAcceptor$$1 codechicken/multipart/TMultiPart] []
    ALOAD 0
    ALOAD 1
    INVOKEINTERFACE TStrictEnergyAcceptor$$1.TStrictEnergyAcceptor$$1$$super$canAddPart (Lcodechicken/multipart/TMultiPart;)Z
    IRETURN
    MAXSTACK = 2
    MAXLOCALS = 2

  // access flags 0x9
  public static transferEnergyToAcceptor(LTStrictEnergyAcceptor$$1;Lnet/minecraftforge/common/util/ForgeDirection;D)D
    ALOAD 0
    INVOKEINTERFACE TStrictEnergyAcceptor$$1.TStrictEnergyAcceptor$$1$$impl ()Lmekanism/api/energy/IStrictEnergyAcceptor;
    ALOAD 1
    DLOAD 2
    INVOKEINTERFACE mekanism/api/energy/IStrictEnergyAcceptor.transferEnergyToAcceptor (Lnet/minecraftforge/common/util/ForgeDirection;D)D
    DRETURN
    MAXSTACK = 4
    MAXLOCALS = 4

  // access flags 0x9
  public static canReceiveEnergy(LTStrictEnergyAcceptor$$1;Lnet/minecraftforge/common/util/ForgeDirection;)Z
    ALOAD 0
    INVOKEINTERFACE TStrictEnergyAcceptor$$1.TStrictEnergyAcceptor$$1$$impl ()Lmekanism/api/energy/IStrictEnergyAcceptor;
    ALOAD 1
    INVOKEINTERFACE mekanism/api/energy/IStrictEnergyAcceptor.canReceiveEnergy (Lnet/minecraftforge/common/util/ForgeDirection;)Z
    IRETURN
    MAXSTACK = 2
    MAXLOCALS = 2

  // access flags 0x9
  public static getEnergy(LTStrictEnergyAcceptor$$1;)D
    ALOAD 0
    INVOKEINTERFACE TStrictEnergyAcceptor$$1.TStrictEnergyAcceptor$$1$$impl ()Lmekanism/api/energy/IStrictEnergyAcceptor;
    INVOKEINTERFACE mekanism/api/energy/IStrictEnergyAcceptor.getEnergy ()D
    DRETURN
    MAXSTACK = 2
    MAXLOCALS = 1

  // access flags 0x9
  public static setEnergy(LTStrictEnergyAcceptor$$1;D)V
    ALOAD 0
    INVOKEINTERFACE TStrictEnergyAcceptor$$1.TStrictEnergyAcceptor$$1$$impl ()Lmekanism/api/energy/IStrictEnergyAcceptor;
    DLOAD 1
    INVOKEINTERFACE mekanism/api/energy/IStrictEnergyAcceptor.setEnergy (D)V
    RETURN
    MAXSTACK = 3
    MAXLOCALS = 3

  // access flags 0x9
  public static getMaxEnergy(LTStrictEnergyAcceptor$$1;)D
    ALOAD 0
    INVOKEINTERFACE TStrictEnergyAcceptor$$1.TStrictEnergyAcceptor$$1$$impl ()Lmekanism/api/energy/IStrictEnergyAcceptor;
    INVOKEINTERFACE mekanism/api/energy/IStrictEnergyAcceptor.getMaxEnergy ()D
    DRETURN
    MAXSTACK = 2
    MAXLOCALS = 1

  // access flags 0x9
  public static copyFrom(LTStrictEnergyAcceptor$$1;Lcodechicken/multipart/TileMultipart;)V
    ALOAD 0
    ALOAD 1
    INVOKEINTERFACE TStrictEnergyAcceptor$$1.TStrictEnergyAcceptor$$1$$super$copyFrom (Lcodechicken/multipart/TileMultipart;)V
    ALOAD 1
    INSTANCEOF TStrictEnergyAcceptor$$1
    IFEQ L0
    ALOAD 0
    ALOAD 1
    INVOKEINTERFACE TStrictEnergyAcceptor$$1.TStrictEnergyAcceptor$$1$$impl ()Lmekanism/api/energy/IStrictEnergyAcceptor;
    INVOKEINTERFACE TStrictEnergyAcceptor$$1.TStrictEnergyAcceptor$$1$$impl_$eq (Lmekanism/api/energy/IStrictEnergyAcceptor;)V
   L0
    RETURN
    MAXSTACK = 2
    MAXLOCALS = 2
}
