// class version 50.0 (50)
// access flags 0x401
public abstract class TTransmitterTile$$5$class {


  // access flags 0x9
  public static $init$(LTTransmitterTile$$5;)V
    RETURN
    MAXSTACK = 1
    MAXLOCALS = 1

  // access flags 0x9
  public static bindPart(LTTransmitterTile$$5;Lcodechicken/multipart/TMultiPart;)V
    ALOAD 0
    ALOAD 1
    INVOKEINTERFACE TTransmitterTile$$5.TTransmitterTile$$5$$super$bindPart (Lcodechicken/multipart/TMultiPart;)V
    ALOAD 1
    INSTANCEOF mekanism/api/transmitters/ITransmitterTile
    IFEQ L0
    ALOAD 0
    ALOAD 1
    CHECKCAST mekanism/api/transmitters/ITransmitterTile
    INVOKEINTERFACE TTransmitterTile$$5.TTransmitterTile$$5$$impl_$eq (Lmekanism/api/transmitters/ITransmitterTile;)V
   L0
   FRAME FULL [TTransmitterTile$$5 codechicken/multipart/TMultiPart] []
    RETURN
    MAXSTACK = 2
    MAXLOCALS = 2

  // access flags 0x9
  public static partRemoved(LTTransmitterTile$$5;Lcodechicken/multipart/TMultiPart;I)V
    ALOAD 0
    ALOAD 1
    ILOAD 2
    INVOKEINTERFACE TTransmitterTile$$5.TTransmitterTile$$5$$super$partRemoved (Lcodechicken/multipart/TMultiPart;I)V
    ALOAD 1
    ALOAD 0
    INVOKEINTERFACE TTransmitterTile$$5.TTransmitterTile$$5$$impl ()Lmekanism/api/transmitters/ITransmitterTile;
    IF_ACMPNE L0
    ALOAD 0
    ACONST_NULL
    INVOKEINTERFACE TTransmitterTile$$5.TTransmitterTile$$5$$impl_$eq (Lmekanism/api/transmitters/ITransmitterTile;)V
   L0
   FRAME FULL [TTransmitterTile$$5 codechicken/multipart/TMultiPart I] []
    RETURN
    MAXSTACK = 3
    MAXLOCALS = 3

  // access flags 0x9
  public static canAddPart(LTTransmitterTile$$5;Lcodechicken/multipart/TMultiPart;)Z
    ALOAD 0
    INVOKEINTERFACE TTransmitterTile$$5.TTransmitterTile$$5$$impl ()Lmekanism/api/transmitters/ITransmitterTile;
    IFNULL L0
    ALOAD 1
    INSTANCEOF mekanism/api/transmitters/ITransmitterTile
    IFEQ L0
    ICONST_0
    IRETURN
   L0
   FRAME FULL [TTransmitterTile$$5 codechicken/multipart/TMultiPart] []
    ALOAD 0
    ALOAD 1
    INVOKEINTERFACE TTransmitterTile$$5.TTransmitterTile$$5$$super$canAddPart (Lcodechicken/multipart/TMultiPart;)Z
    IRETURN
    MAXSTACK = 2
    MAXLOCALS = 2

  // access flags 0x9
  public static getTransmitter(LTTransmitterTile$$5;)Lmekanism/api/transmitters/IGridTransmitter;
    ALOAD 0
    INVOKEINTERFACE TTransmitterTile$$5.TTransmitterTile$$5$$impl ()Lmekanism/api/transmitters/ITransmitterTile;
    INVOKEINTERFACE mekanism/api/transmitters/ITransmitterTile.getTransmitter ()Lmekanism/api/transmitters/IGridTransmitter;
    ARETURN
    MAXSTACK = 1
    MAXLOCALS = 1

  // access flags 0x9
  public static copyFrom(LTTransmitterTile$$5;Lcodechicken/multipart/TileMultipart;)V
    ALOAD 0
    ALOAD 1
    INVOKEINTERFACE TTransmitterTile$$5.TTransmitterTile$$5$$super$copyFrom (Lcodechicken/multipart/TileMultipart;)V
    ALOAD 1
    INSTANCEOF TTransmitterTile$$5
    IFEQ L0
    ALOAD 0
    ALOAD 1
    INVOKEINTERFACE TTransmitterTile$$5.TTransmitterTile$$5$$impl ()Lmekanism/api/transmitters/ITransmitterTile;
    INVOKEINTERFACE TTransmitterTile$$5.TTransmitterTile$$5$$impl_$eq (Lmekanism/api/transmitters/ITransmitterTile;)V
   L0
    RETURN
    MAXSTACK = 2
    MAXLOCALS = 2
}
